HomemadeRandom/HomemadeRandom.py
HomemadeRandom/__init__.py
HomemadeRandom/test.py
HomemadeRandom/base_rv_generators/__init__.py
HomemadeRandom/base_rv_generators/rv_generators.py
HomemadeRandom-0.1.7.dist-info/LICENSE.txt
HomemadeRandom-0.1.7.dist-info/METADATA
HomemadeRandom-0.1.7.dist-info/WHEEL
HomemadeRandom-0.1.7.dist-info/top_level.txt
HomemadeRandom-0.1.7.dist-info/RECORD
