Metadata-Version: 2.1
Name: HomemadeRandom
Version: 0.1.7
Summary: A random number generator built from scratch for ISYE6644 class project
Home-page: https://github.com/dstar30/HomemadeRandom
Author: Daniel Jiang
License: MIT license
Platform: UNKNOWN
Classifier: Programming Language :: Python :: 3.7
Classifier: License :: OSI Approved :: MIT License
